odoo/addons/ssi_fixed_asset_report/README.rst
odoo/addons/ssi_fixed_asset_report/__init__.py
odoo/addons/ssi_fixed_asset_report/__manifest__.py
odoo/addons/ssi_fixed_asset_report/reports.xml
odoo/addons/ssi_fixed_asset_report/i18n/id.po
odoo/addons/ssi_fixed_asset_report/i18n/ssi_fixed_asset_report.pot
odoo/addons/ssi_fixed_asset_report/report/__init__.py
odoo/addons/ssi_fixed_asset_report/report/fixed_asset_yearly_xlsx.py
odoo/addons/ssi_fixed_asset_report/report/templates/fixed_asset_yearly.xml
odoo/addons/ssi_fixed_asset_report/report/templates/layouts.xml
odoo/addons/ssi_fixed_asset_report/security/ir.model.access.csv
odoo/addons/ssi_fixed_asset_report/static/description/icon.png
odoo/addons/ssi_fixed_asset_report/static/src/css/report.css
odoo/addons/ssi_fixed_asset_report/static/src/js/action_manager_report.js
odoo/addons/ssi_fixed_asset_report/static/src/js/client_action.js
odoo/addons/ssi_fixed_asset_report/static/src/js/report.js
odoo/addons/ssi_fixed_asset_report/static/src/xml/report.xml
odoo/addons/ssi_fixed_asset_report/views/report_template.xml
odoo/addons/ssi_fixed_asset_report/wizards/__init__.py
odoo/addons/ssi_fixed_asset_report/wizards/wizard_fixed_asset_yearly.py
odoo/addons/ssi_fixed_asset_report/wizards/wizard_fixed_yearly_asset.xml
odoo14_addon_ssi_fixed_asset_report-14.0.1.8.0.dist-info/METADATA
odoo14_addon_ssi_fixed_asset_report-14.0.1.8.0.dist-info/WHEEL
odoo14_addon_ssi_fixed_asset_report-14.0.1.8.0.dist-info/top_level.txt
odoo14_addon_ssi_fixed_asset_report-14.0.1.8.0.dist-info/RECORD
